whitson/client/__init__.py
whitson/client/_api_client.py
whitson/client/_whitson_client.py
whitson/client/api/__init__.py
whitson/client/api/fields.py
whitson/client/api/production_data.py
whitson/client/api/projects.py
whitson/client/api/wells.py
whitson/client/config.py
whitson/client/dataclasses.py
whitson_sdk_python-0.4.0.dist-info/LICENSE.txt
whitson_sdk_python-0.4.0.dist-info/METADATA
whitson_sdk_python-0.4.0.dist-info/WHEEL
whitson_sdk_python-0.4.0.dist-info/RECORD
