Metadata-Version: 2.1
Name: whitson-sdk-python
Version: 0.4.0
Summary: Whitson Python SDK for developers, data scientists, and engineers working with Whitson+
License: MIT
Author: Angela Dang Atkinson
Author-email: Angela.DangAtkinson@ovintiv.com
Requires-Python: >=3.9,<4.0
Classifier: License :: OSI Approved :: MIT License
Classifier: Programming Language :: Python :: 3
Classifier: Programming Language :: Python :: 3.9
Classifier: Programming Language :: Python :: 3.10
Classifier: Programming Language :: Python :: 3.11
Classifier: Programming Language :: Python :: 3.12
Requires-Dist: dacite (>=1.8.1,<2.0.0)
Requires-Dist: requests (>=2.31.0,<3.0.0)
